ansitcontrib/vagrant/__init__.py
ansitcontrib_vagrant-0.2.0.dist-info/METADATA
ansitcontrib_vagrant-0.2.0.dist-info/RECORD
ansitcontrib_vagrant-0.2.0.dist-info/WHEEL
ansitcontrib_vagrant-0.2.0.dist-info/top_level.txt
